{"cameraMode":{"drawMode":0,"name":"Shaded","section":"Shading Mode"},"sceneLighting":true,"audioPlay":false,"sceneViewState":{"showFog":true,"showMaterialUpdate":false,"showSkybox":true,"showFlares":true,"showImageEffects":true,"showParticleSystems":true},"in2DMode":false,"pivot":{"x":-0.006598472595214844,"y":0.18917036056518556,"z":-0.12183094024658203},"rotation":{"x":-0.36848077178001406,"y":0.5256144404411316,"z":-0.2698502540588379,"w":-0.7177271246910095},"size":48.5213737487793,"orthographic":false}